plover_python_dictionary_cmd/__init__.py
plover_python_dictionary_cmd/py.typed
plover_python_dictionary_cmd-0.0.1.dist-info/LICENSE
plover_python_dictionary_cmd-0.0.1.dist-info/METADATA
plover_python_dictionary_cmd-0.0.1.dist-info/WHEEL
plover_python_dictionary_cmd-0.0.1.dist-info/entry_points.txt
plover_python_dictionary_cmd-0.0.1.dist-info/top_level.txt
plover_python_dictionary_cmd-0.0.1.dist-info/zip-safe
plover_python_dictionary_cmd-0.0.1.dist-info/RECORD
