Metadata-Version: 2.2
Name: plover_python_dictionary_cmd
Version: 0.0.1
Summary: Execute arbitrary command from a Python dictionary
Home-page: https://github.com/user202729/plover-python-dictionary-cmd
Author: user202729
License: GNU General Public License v3 or later (GPLv3+)
Keywords: plover plover_plugin
Classifier: Environment :: Plugins
Classifier: License :: OSI Approved :: GNU General Public License v3 or later (GPLv3+)
Classifier: Operating System :: OS Independent
Classifier: Programming Language :: Python :: 3
License-File: LICENSE
Requires-Dist: plover>=4.0.0.dev8
